yunke_langfuse/__init__.py
yunke_langfuse/api/__init__.py
yunke_langfuse/api/client.py
yunke_langfuse/api/core/__init__.py
yunke_langfuse/api/core/api_error.py
yunke_langfuse/api/core/client_wrapper.py
yunke_langfuse/api/core/datetime_utils.py
yunke_langfuse/api/core/jsonable_encoder.py
yunke_langfuse/api/core/remove_none_from_dict.py
yunke_langfuse/api/resources/__init__.py
yunke_langfuse/api/resources/commons/__init__.py
yunke_langfuse/api/resources/commons/errors/__init__.py
yunke_langfuse/api/resources/commons/errors/access_denied_error.py
yunke_langfuse/api/resources/commons/errors/error.py
yunke_langfuse/api/resources/commons/errors/method_not_allowed_error.py
yunke_langfuse/api/resources/commons/errors/not_found_error.py
yunke_langfuse/api/resources/commons/errors/unauthorized_error.py
yunke_langfuse/api/resources/commons/types/__init__.py
yunke_langfuse/api/resources/commons/types/dataset.py
yunke_langfuse/api/resources/commons/types/dataset_item.py
yunke_langfuse/api/resources/commons/types/dataset_run.py
yunke_langfuse/api/resources/commons/types/dataset_run_item.py
yunke_langfuse/api/resources/commons/types/dataset_status.py
yunke_langfuse/api/resources/commons/types/map_value.py
yunke_langfuse/api/resources/commons/types/model_usage_unit.py
yunke_langfuse/api/resources/commons/types/observation.py
yunke_langfuse/api/resources/commons/types/observation_level.py
yunke_langfuse/api/resources/commons/types/score.py
yunke_langfuse/api/resources/commons/types/session.py
yunke_langfuse/api/resources/commons/types/session_with_traces.py
yunke_langfuse/api/resources/commons/types/trace.py
yunke_langfuse/api/resources/commons/types/trace_with_details.py
yunke_langfuse/api/resources/commons/types/trace_with_full_details.py
yunke_langfuse/api/resources/commons/types/usage.py
yunke_langfuse/api/resources/dataset_items/__init__.py
yunke_langfuse/api/resources/dataset_items/client.py
yunke_langfuse/api/resources/dataset_items/types/__init__.py
yunke_langfuse-2.7.6.dist-info/LICENSE
yunke_langfuse-2.7.6.dist-info/METADATA
yunke_langfuse-2.7.6.dist-info/WHEEL
yunke_langfuse-2.7.6.dist-info/RECORD
