Metadata-Version: 2.1
Name: yunke_langfuse
Version: 2.7.6
Summary: A client library for accessing langfuse
License: MIT
Author: langfuse
Author-email: developers@langfuse.com
Requires-Python: >=3.8.1,<4.0
Classifier: License :: OSI Approved :: MIT License
Classifier: Programming Language :: Python :: 3
Classifier: Programming Language :: Python :: 3.9
Classifier: Programming Language :: Python :: 3.10
Classifier: Programming Language :: Python :: 3.11
Classifier: Programming Language :: Python :: 3.12
Provides-Extra: langchain
Requires-Dist: backoff (>=2.2.1,<3.0.0)
Requires-Dist: chevron (>=0.14.0,<0.15.0)
Requires-Dist: httpx (>=0.15.4,<0.26.0)
Requires-Dist: langchain (>=0.0.309) ; extra == "langchain"
Requires-Dist: openai (>=0.27.8)
Requires-Dist: pydantic (>=1.10.7,<3.0)
Requires-Dist: wrapt (==1.14.1)
